icd9cms/__init__.py
icd9cms/icd9.py
icd9cms/data/CMS32_DESC_LONG_SHORT_DX.xlsx
icd9cms/data/hierarchy.pickle
icd9cms-0.2.1.dist-info/METADATA
icd9cms-0.2.1.dist-info/RECORD
icd9cms-0.2.1.dist-info/WHEEL
icd9cms-0.2.1.dist-info/top_level.txt
