Metadata-Version: 2.1
Name: icd9cms
Version: 0.2.1
Summary: A utility for searching across the full icd9cms (2015) diagnosis hierarchy
Home-page: https://github.com/tomolopolis/icd-util
Author: Tom Searle
Author-email: thomas.searle@kcl.ac.uk
License: UNKNOWN
Platform: UNKNOWN
Classifier: Programming Language :: Python :: 3
Classifier: License :: OSI Approved :: MIT License
Classifier: Operating System :: OS Independent
Requires-Dist: pandas
Requires-Dist: bs4
Requires-Dist: requests
